superinvoke/__init__.py
superinvoke/collections/__init__.py
superinvoke/collections/env.py
superinvoke/collections/misc.py
superinvoke/collections/tool.py
superinvoke/constants.py
superinvoke/extensions/__init__.py
superinvoke/extensions/collection.py
superinvoke/extensions/context.py
superinvoke/extensions/task.py
superinvoke/main.py
superinvoke/objects/__init__.py
superinvoke/objects/common.py
superinvoke/objects/env.py
superinvoke/objects/tool.py
superinvoke/utils.py
superinvoke-1.0.6.dist-info/LICENSE
superinvoke-1.0.6.dist-info/METADATA
superinvoke-1.0.6.dist-info/WHEEL
superinvoke-1.0.6.dist-info/RECORD
